{"v":3,"stories":{"introduction--introduction":{"id":"introduction--introduction","name":"Introduction","title":"Introduction","importPath":"./components/stories/Introduction.stories.tsx","tags":["story"],"kind":"Introduction","story":"Introduction","parameters":{"__id":"introduction--introduction","docsOnly":false,"fileName":"./components/stories/Introduction.stories.tsx"}},"tribe--tribe-live":{"id":"tribe--tribe-live","name":"Tribe","title":"Tribe","importPath":"./components/stories/TribeLive.stories.tsx","tags":["story"],"kind":"Tribe","story":"Tribe","parameters":{"__id":"tribe--tribe-live","docsOnly":false,"fileName":"./components/stories/TribeLive.stories.tsx"}},"components-clientprofile--docs":{"id":"components-clientprofile--docs","title":"Components/ClientProfile","name":"Docs","importPath":"./components/stories/ClientProfile.stories.tsx","tags":["autodocs","docs"],"storiesImports":[],"kind":"Components/ClientProfile","story":"Docs","parameters":{"__id":"components-clientprofile--docs","docsOnly":true,"fileName":"./components/stories/ClientProfile.stories.tsx"}},"components-clientprofile--default":{"id":"components-clientprofile--default","name":"Default","title":"Components/ClientProfile","importPath":"./components/stories/ClientProfile.stories.tsx","tags":["autodocs","story"],"kind":"Components/ClientProfile","story":"Default","parameters":{"__id":"components-clientprofile--default","docsOnly":false,"fileName":"./components/stories/ClientProfile.stories.tsx"}},"components-clientprofile--custom-styling":{"id":"components-clientprofile--custom-styling","name":"Custom Styling","title":"Components/ClientProfile","importPath":"./components/stories/ClientProfile.stories.tsx","tags":["autodocs","story"],"kind":"Components/ClientProfile","story":"Custom Styling","parameters":{"__id":"components-clientprofile--custom-styling","docsOnly":false,"fileName":"./components/stories/ClientProfile.stories.tsx"}},"components-clientcardlg--docs":{"id":"components-clientcardlg--docs","title":"Components/ClientCardLG","name":"Docs","importPath":"./components/stories/ClientCardLG.stories.tsx","tags":["autodocs","docs"],"storiesImports":[],"kind":"Components/ClientCardLG","story":"Docs","parameters":{"__id":"components-clientcardlg--docs","docsOnly":true,"fileName":"./components/stories/ClientCardLG.stories.tsx"}},"components-clientcardlg--default":{"id":"components-clientcardlg--default","name":"Default","title":"Components/ClientCardLG","importPath":"./components/stories/ClientCardLG.stories.tsx","tags":["autodocs","story"],"kind":"Components/ClientCardLG","story":"Default","parameters":{"__id":"components-clientcardlg--default","docsOnly":false,"fileName":"./components/stories/ClientCardLG.stories.tsx"}},"components-clientcardlg--custom-styling":{"id":"components-clientcardlg--custom-styling","name":"Custom Styling","title":"Components/ClientCardLG","importPath":"./components/stories/ClientCardLG.stories.tsx","tags":["autodocs","story"],"kind":"Components/ClientCardLG","story":"Custom Styling","parameters":{"__id":"components-clientcardlg--custom-styling","docsOnly":false,"fileName":"./components/stories/ClientCardLG.stories.tsx"}},"components-clientcardsm--docs":{"id":"components-clientcardsm--docs","title":"Components/ClientCardSM","name":"Docs","importPath":"./components/stories/ClientCardSM.stories.tsx","tags":["autodocs","docs"],"storiesImports":[],"kind":"Components/ClientCardSM","story":"Docs","parameters":{"__id":"components-clientcardsm--docs","docsOnly":true,"fileName":"./components/stories/ClientCardSM.stories.tsx"}},"components-clientcardsm--default":{"id":"components-clientcardsm--default","name":"Default","title":"Components/ClientCardSM","importPath":"./components/stories/ClientCardSM.stories.tsx","tags":["autodocs","story"],"kind":"Components/ClientCardSM","story":"Default","parameters":{"__id":"components-clientcardsm--default","docsOnly":false,"fileName":"./components/stories/ClientCardSM.stories.tsx"}},"components-clientcardsm--custom-styling":{"id":"components-clientcardsm--custom-styling","name":"Custom Styling","title":"Components/ClientCardSM","importPath":"./components/stories/ClientCardSM.stories.tsx","tags":["autodocs","story"],"kind":"Components/ClientCardSM","story":"Custom Styling","parameters":{"__id":"components-clientcardsm--custom-styling","docsOnly":false,"fileName":"./components/stories/ClientCardSM.stories.tsx"}},"components-clientlist--docs":{"id":"components-clientlist--docs","title":"Components/ClientList","name":"Docs","importPath":"./components/stories/ClientList.stories.tsx","tags":["autodocs","docs"],"storiesImports":[],"kind":"Components/ClientList","story":"Docs","parameters":{"__id":"components-clientlist--docs","docsOnly":true,"fileName":"./components/stories/ClientList.stories.tsx"}},"components-clientlist--default":{"id":"components-clientlist--default","name":"Default","title":"Components/ClientList","importPath":"./components/stories/ClientList.stories.tsx","tags":["autodocs","story"],"kind":"Components/ClientList","story":"Default","parameters":{"__id":"components-clientlist--default","docsOnly":false,"fileName":"./components/stories/ClientList.stories.tsx"}},"components-clientlist--custom-styling":{"id":"components-clientlist--custom-styling","name":"Custom Styling","title":"Components/ClientList","importPath":"./components/stories/ClientList.stories.tsx","tags":["autodocs","story"],"kind":"Components/ClientList","story":"Custom Styling","parameters":{"__id":"components-clientlist--custom-styling","docsOnly":false,"fileName":"./components/stories/ClientList.stories.tsx"}},"components-leaderboard--docs":{"id":"components-leaderboard--docs","title":"Components/Leaderboard","name":"Docs","importPath":"./components/stories/Leaderboard.stories.tsx","tags":["autodocs","docs"],"storiesImports":[],"kind":"Components/Leaderboard","story":"Docs","parameters":{"__id":"components-leaderboard--docs","docsOnly":true,"fileName":"./components/stories/Leaderboard.stories.tsx"}},"components-leaderboard--default":{"id":"components-leaderboard--default","name":"Default","title":"Components/Leaderboard","importPath":"./components/stories/Leaderboard.stories.tsx","tags":["autodocs","story"],"kind":"Components/Leaderboard","story":"Default","parameters":{"__id":"components-leaderboard--default","docsOnly":false,"fileName":"./components/stories/Leaderboard.stories.tsx"}},"components-leaderboard--all-time":{"id":"components-leaderboard--all-time","name":"All Time","title":"Components/Leaderboard","importPath":"./components/stories/Leaderboard.stories.tsx","tags":["autodocs","story"],"kind":"Components/Leaderboard","story":"All Time","parameters":{"__id":"components-leaderboard--all-time","docsOnly":false,"fileName":"./components/stories/Leaderboard.stories.tsx"}},"components-leaderboard--weekly":{"id":"components-leaderboard--weekly","name":"Weekly","title":"Components/Leaderboard","importPath":"./components/stories/Leaderboard.stories.tsx","tags":["autodocs","story"],"kind":"Components/Leaderboard","story":"Weekly","parameters":{"__id":"components-leaderboard--weekly","docsOnly":false,"fileName":"./components/stories/Leaderboard.stories.tsx"}},"components-leaderboard--monthly":{"id":"components-leaderboard--monthly","name":"Monthly","title":"Components/Leaderboard","importPath":"./components/stories/Leaderboard.stories.tsx","tags":["autodocs","story"],"kind":"Components/Leaderboard","story":"Monthly","parameters":{"__id":"components-leaderboard--monthly","docsOnly":false,"fileName":"./components/stories/Leaderboard.stories.tsx"}},"components-leaderboard--custom-badge":{"id":"components-leaderboard--custom-badge","name":"Custom Badge","title":"Components/Leaderboard","importPath":"./components/stories/Leaderboard.stories.tsx","tags":["autodocs","story"],"kind":"Components/Leaderboard","story":"Custom Badge","parameters":{"__id":"components-leaderboard--custom-badge","docsOnly":false,"fileName":"./components/stories/Leaderboard.stories.tsx"}},"components-leaderboard--with-badge-filter":{"id":"components-leaderboard--with-badge-filter","name":"With Badge Filter","title":"Components/Leaderboard","importPath":"./components/stories/Leaderboard.stories.tsx","tags":["autodocs","story"],"kind":"Components/Leaderboard","story":"With Badge Filter","parameters":{"__id":"components-leaderboard--with-badge-filter","docsOnly":false,"fileName":"./components/stories/Leaderboard.stories.tsx"}},"components-leaderboard--custom-styling":{"id":"components-leaderboard--custom-styling","name":"Custom Styling","title":"Components/Leaderboard","importPath":"./components/stories/Leaderboard.stories.tsx","tags":["autodocs","story"],"kind":"Components/Leaderboard","story":"Custom Styling","parameters":{"__id":"components-leaderboard--custom-styling","docsOnly":false,"fileName":"./components/stories/Leaderboard.stories.tsx"}},"components-userlist--docs":{"id":"components-userlist--docs","title":"Components/UserList","name":"Docs","importPath":"./components/stories/UserList.stories.tsx","tags":["autodocs","docs"],"storiesImports":[],"kind":"Components/UserList","story":"Docs","parameters":{"__id":"components-userlist--docs","docsOnly":true,"fileName":"./components/stories/UserList.stories.tsx"}},"components-userlist--default":{"id":"components-userlist--default","name":"Default","title":"Components/UserList","importPath":"./components/stories/UserList.stories.tsx","tags":["autodocs","story"],"kind":"Components/UserList","story":"Default","parameters":{"__id":"components-userlist--default","docsOnly":false,"fileName":"./components/stories/UserList.stories.tsx"}},"components-userlist--custom-styling":{"id":"components-userlist--custom-styling","name":"Custom Styling","title":"Components/UserList","importPath":"./components/stories/UserList.stories.tsx","tags":["autodocs","story"],"kind":"Components/UserList","story":"Custom Styling","parameters":{"__id":"components-userlist--custom-styling","docsOnly":false,"fileName":"./components/stories/UserList.stories.tsx"}}}}
